VHDL_P2.vhd
library IEEE;
use IEEE.std_logic_1164.all;
use IEEE.numeric_std.all;

entity VHDL_P2 is
    port(
        A: IN STD_LOGIC_VECTOR(3 DOWNTO 0) := "0100";
        B: IN STD_LOGIC_VECTOR(3 DOWNTO 0) := "0001";
        R: OUT STD_LOGIC_VECTOR(3 DOWNTO 0)
    );
end entity VHDL_P2;

architecture rtl of VHDL_P2 is
    signal OP: unsigned(2 downto 0) := "000";
begin
    process is
    begin
        wait for 10 ns;
        OP <= OP + 1;
        wait for 10 ns;
        OP <= OP + 1;
        wait for 10 ns;
        OP <= OP + 1;
        wait for 10 ns;
        OP <= OP + 1;
        wait for 10 ns;
        OP <= OP + 1;
        wait for 10 ns;
        OP <= OP + 1;
        wait for 10 ns;
        OP <= OP + 1;
        wait for 10 ns;
        OP <= OP+1;
        wait;
    end process;
    
    mux: process (A, B, OP)
    begin
        case OP is
            when "000" =>
                R <= "0000";
            when "001" =>
                R <= "1111";
            when "010" =>
                R <= STD_LOGIC_VECTOR(SIGNED(A) - SIGNED(B));
            when "011" =>
                R <= STD_LOGIC_VECTOR(SIGNED(A) + SIGNED(B));
            when "100" =>
                R <= A AND B;
            when "101" =>
                R <= not(A AND B);
            when "110" =>
                R <= A OR B;
            when others =>
                R <= not(A OR B);
        end case;
    end process;
end architecture rtl;

VHDL_P2.vcd
$date
  Tue Apr 12 20:41:31 2022
$end
$version
  GHDL v0
$end
$timescale
  1 fs
$end
$scope module standard $end
$upscope $end
$scope module std_logic_1164 $end
$upscope $end
$scope module numeric_std $end
$upscope $end
$scope module vhdl_p2 $end
$var reg 4 ! a[3:0] $end
$var reg 4 " b[3:0] $end
$var reg 4 # r[3:0] $end
$var reg 3 $ op[2:0] $end
$upscope $end
$enddefinitions $end
#0
b0100 !
b0001 "
b0000 #
b000 $
#10000000
b1111 #
b001 $
#20000000
b0011 #
b010 $
#30000000
b0101 #
b011 $
#40000000
b0000 #
b100 $
#50000000
b1111 #
b101 $
#60000000
b0101 #
b110 $
#70000000
b1010 #
b111 $
#80000000
b0000 #
b000 $
